hashring/__init__.py
hashring/hashring.py
hashring-1.5.1.dist-info/DESCRIPTION.rst
hashring-1.5.1.dist-info/entry_points.txt
hashring-1.5.1.dist-info/METADATA
hashring-1.5.1.dist-info/metadata.json
hashring-1.5.1.dist-info/RECORD
hashring-1.5.1.dist-info/top_level.txt
hashring-1.5.1.dist-info/WHEEL
